grasia_dash_components/__init__.py
grasia_dash_components/bundle.js
grasia_dash_components/bundle.js.map
grasia_dash_components/metadata.json
grasia_dash_components/version.py
grasia_dash_components-0.3.3.dist-info/METADATA
grasia_dash_components-0.3.3.dist-info/RECORD
grasia_dash_components-0.3.3.dist-info/WHEEL
grasia_dash_components-0.3.3.dist-info/top_level.txt
