Metadata-Version: 2.1
Name: grasia-dash-components
Version: 0.3.3
Summary: Extended dash UI component suite for @GRASIA.
Home-page: https://github.com/Grasia/grasia-dash-components
Author: Abel 'Akronix' Serrano Juste
Author-email: akronix5@gmail.com
License: MIT
Keywords: dash react-components grasia
Platform: UNKNOWN
Requires-Python: >=3
Requires-Dist: dash
Requires-Dist: dash-renderer
